nonebot_plugin_error_report/__init__.py
nonebot_plugin_error_report/config.py
nonebot_plugin_error_report/email.py
nonebot_plugin_error_report/model.py
nonebot_plugin_error_report/toimg.py
nonebot_plugin_error_report-0.1.0.dist-info/LICENSE
nonebot_plugin_error_report-0.1.0.dist-info/METADATA
nonebot_plugin_error_report-0.1.0.dist-info/WHEEL
nonebot_plugin_error_report-0.1.0.dist-info/top_level.txt
nonebot_plugin_error_report-0.1.0.dist-info/RECORD
