Metadata-Version: 2.1
Name: nonebot-plugin-error-report
Version: 0.1.0
Summary: 基于nonebot的报错处理插件，支持图片/文字发送、数据库存储及跨平台
Home-page: https://github.com/huanxin996/nonebot_plugin_error_report
Author: huanxin996
Author-email: mc.xiaolang@foxmail.com
Classifier: Programming Language :: Python :: 3
Classifier: License :: OSI Approved :: MIT License
Classifier: Operating System :: OS Independent
License-File: LICENSE
Requires-Dist: nonebot2<3.0.0,>=2.3.0
Requires-Dist: nonebot-plugin-alconna>=0.54.0
Requires-Dist: nonebot-plugin-tortoise-orm<0.2.0,>=0.1.0
Requires-Dist: nonebot-plugin-userinfo<0.3.0,>=0.2.0
Requires-Dist: nonebot-plugin-apscheduler<0.6.0,>=0.3.0
Requires-Dist: pillow<12.0.0,>=9.0.0
Requires-Dist: aiosmtplib<5.0.0,>=2.0.0
Requires-Dist: aiohttp>=3.0.0
